MANIFEST.in
README.rst
setup.py
glacier_tool.egg-info/PKG-INFO
glacier_tool.egg-info/SOURCES.txt
glacier_tool.egg-info/dependency_links.txt
glacier_tool.egg-info/not-zip-safe
glacier_tool.egg-info/requires.txt
glacier_tool.egg-info/top_level.txt
gt/__init__.py
gt/resources/README.rst
gt/resources/requirements.txt
gt/resources/scripts/gt_upload_large