Metadata-Version: 1.0
Name: glacier-tool
Version: 0.2.3
Summary: Do concurrent, multipart uploads of massive archives to Amazon Glacier.
Home-page: https://github.com/dsoprea/GlacierTool
Author: Dustin Oprea
Author-email: myselfasunder@gmail.com
License: GPL 2
Keywords: glacier concurrent
Platform: UNKNOWN
